torchelastic/__init__.py
torchelastic/version.py
torchelastic/agent/__init__.py
torchelastic/agent/server/__init__.py
torchelastic/agent/server/api.py
torchelastic/agent/server/local_elastic_agent.py
torchelastic/distributed/__init__.py
torchelastic/distributed/argparse_util.py
torchelastic/distributed/launch.py
torchelastic/events/__init__.py
torchelastic/events/api.py
torchelastic/events/handlers.py
torchelastic/metrics/__init__.py
torchelastic/metrics/api.py
torchelastic/multiprocessing/__init__.py
torchelastic/multiprocessing/api.py
torchelastic/multiprocessing/redirects.py
torchelastic/multiprocessing/tail_log.py
torchelastic/multiprocessing/errors/__init__.py
torchelastic/multiprocessing/errors/error_handler.py
torchelastic/multiprocessing/errors/handlers.py
torchelastic/rendezvous/__init__.py
torchelastic/rendezvous/api.py
torchelastic/rendezvous/etcd_rendezvous.py
torchelastic/rendezvous/etcd_server.py
torchelastic/rendezvous/registry.py
torchelastic/rendezvous/utils.py
torchelastic/timer/__init__.py
torchelastic/timer/api.py
torchelastic/timer/local_timer.py
torchelastic/tsm/__init__.py
torchelastic/tsm/driver/__init__.py
torchelastic/tsm/driver/api.py
torchelastic/tsm/driver/local_scheduler.py
torchelastic/tsm/driver/schedulers.py
torchelastic/tsm/driver/standalone_session.py
torchelastic/utils/__init__.py
torchelastic/utils/api.py
torchelastic/utils/distributed.py
torchelastic/utils/logging.py
torchelastic/utils/store.py
torchelastic/utils/data/__init__.py
torchelastic/utils/data/cycling_iterator.py
torchelastic/utils/data/elastic_distributed_sampler.py
torchelastic-0.2.2.dist-info/LICENSE
torchelastic-0.2.2.dist-info/METADATA
torchelastic-0.2.2.dist-info/WHEEL
torchelastic-0.2.2.dist-info/top_level.txt
torchelastic-0.2.2.dist-info/RECORD
