Metadata-Version: 2.1
Name: torchelastic
Version: 0.2.2
Summary: PyTorch Elastic Training
Home-page: https://github.com/pytorch/elastic
Author: PyTorch Elastic Devs
Author-email: torchelastic@fb.com
License: BSD-3
Keywords: pytorch,machine learning,elastic,distributed
Platform: UNKNOWN
Classifier: Development Status :: 4 - Beta
Classifier: Intended Audience :: Developers
Classifier: Intended Audience :: Science/Research
Classifier: License :: OSI Approved :: BSD License
Classifier: Programming Language :: Python :: 3
Classifier: Programming Language :: Python :: 3.8
Classifier: Topic :: System :: Distributed Computing
Classifier: Topic :: Scientific/Engineering :: Artificial Intelligence
Requires-Python: >=3.8
Requires-Dist: numpy
Requires-Dist: python-etcd (>=0.4.5)
Requires-Dist: torch (>=1.8.0dev)
